[
  {
    "topic": "Perfekt mit haben",
    "level": "A2",
    "explanation_tr": "Geçmiş zamanı anlatmak için 'haben' + Partizip II kullanılır. Örnek: Ich habe gegessen (Yemek yedim). Düzenli fiillerde Partizip II genellikle 'ge-' öneki ve '-t' son eki ile oluşur.",
    "examples": [
      {
        "de": "Ich habe gegessen.",
        "tr": "Yemek yedim."
      },
      {
        "de": "Er hat gearbeitet.",
        "tr": "O çalıştı."
      },
      {
        "de": "Wir haben gespielt.",
        "tr": "Biz oynadık."
      }
    ]
  }
]







